{
    "T16n0657_010:0203a02": "佛說華手經卷第十",
    "T16n0657_010:0203a04": "後秦龜茲國三藏鳩摩羅什奉　詔譯",
    "T16n0657_010:0203a05": "34 法門品(一〇)法門品第三十四",
    "T16n0657_010:0203a06": "佛告堅意：「法名無思、無慮、無相、無作、無憶、無",
    "T16n0657_010:0203a07": "念，淨妙無緣，無有文字，亦無言說，不可顯",
    "T16n0657_010:0203a08": "示。堅意！諸法不會諸根，不可以智知，不可以",
    "T16n0657_010:0203a09": "無智知，非可知非不可知。「復次，堅意！法名眾",
    "T16n0657_010:0203a10": "緣所成，如來能知，而如來知不可言說。而",
    "T16n0657_010:0203a11": "如來以不可說法，說是諸法，所有說道即是",
    "T16n0657_010:0203a12": "法門。何以故？以諸行印印一切法，令一味故。",
    "T16n0657_010:0203a13": "堅意！諸法無盡，盡際無盡故。堅意！諸法畢",
    "T16n0657_010:0203a14": "竟不增不減，入盡際故。以是義故，如來以",
    "T16n0657_010:0203a15": "語言、文字分別解說。「堅意！阿字門入一切法，",
    "T16n0657_010:0203a16": "以阿字門分別諸法。先入阿字門，然後餘字",
    "T16n0657_010:0203a17": "次第相續。是故言從阿字邊變出諸字，從諸",
    "T16n0657_010:0203a18": "字邊會成諸句，以諸句故能成諸義，是故如",
    "T16n0657_010:0203a19": "來說阿字門入一切法。堅意！此是法門。何等",
    "T16n0657_010:0203a20": "是法？堅意！所謂法者，本來無作、無說、無示，無",
    "T16n0657_010:0203a21": "知故知、無說故說、無示故示。如是阿字，能作",
    "T16n0657_010:0203a22": "是一切語言，是名法門。若善男子、善女人",
    "T16n0657_010:0203a23": "入是門者，得無盡慧及無盡辯。其無盡者，過",
    "T16n0657_010:0203a24": "去無盡，無盡盡中無相、無說，諸有所知皆為",
    "T16n0657_010:0203a25": "無知，諸有所示皆為無示，有所分別皆無分",
    "T16n0657_010:0203a26": "別，故名無盡。堅意！是名為門。是為何門？",
    "T16n0657_010:0203a27": "是諸法門。何等是法？佛所不得。又此門者，觀",
    "T16n0657_010:0203a28": "一切法入無思慮。何以故？一切語言皆非語",
    "T16n0657_010:0203a29": "言，一切言說皆無有盡，一切言語皆如不離",
    "T16n0657_010:0203b01": "如，一切智皆非智。堅意！是名金剛句也。何",
    "T16n0657_010:0203b02": "以故名為金剛句耶？若法無作則不可壞，",
    "T16n0657_010:0203b03": "不可壞故名金剛句。諸法無業，若無有業則",
    "T16n0657_010:0203b04": "無有報；是故如來說一切法無業、無報，是",
    "T16n0657_010:0203b05": "名法印。如來所可說業、說報皆以是印，是印",
    "T16n0657_010:0203b06": "不可破壞。堅意！若善男子、善女人欲知業報",
    "T16n0657_010:0203b07": "當入是門。「堅意！一切諸法無來無去，是入法",
    "T16n0657_010:0203b08": "門。我因是門，為眾生說生死差別。堅意！若",
    "T16n0657_010:0203b09": "善男子，善女人欲入眾生生死智者，以是印",
    "T16n0657_010:0203b10": "入，是名法印，名無文字印、無障礙印。堅意！如",
    "T16n0657_010:0203b11": "來有所言說，皆以是印。一切有身皆如來身。",
    "T16n0657_010:0203b12": "何以故？是諸身性不相違背，佛以是印說",
    "T16n0657_010:0203b13": "眾生身相，是名身印。又以是印顯示演說一",
    "T16n0657_010:0203b14": "切身相。何以故？堅意！諸法無門，不可入故；",
    "T16n0657_010:0203b15": "法不可入，以不出故；諸法無出，不可入故。是",
    "T16n0657_010:0203b16": "故如來若有所說，皆不離是無礙際說，以無",
    "T16n0657_010:0203b17": "礙際說一切法，亦以是際知諸眾生隨宜為",
    "T16n0657_010:0203b18": "說。「堅意！無礙際者即無邊際，無邊際者即是",
    "T16n0657_010:0203b19": "一切眾生性也，是名際門。入是際門，則能開",
    "T16n0657_010:0203b20": "演千億法藏。此法藏者，即非藏也。堅意！如來",
    "T16n0657_010:0203b21": "眾法藏中，有所說法，皆說是際。復有色藏，受、",
    "T16n0657_010:0203b22": "想、行、識藏，是藏，非藏，不自在藏，是名諸藏以",
    "T16n0657_010:0203b23": "阿字門入。」爾時，堅意白佛言：「世尊！是門甚深。」",
    "T16n0657_010:0203b24": "佛言：「堅意！我不生念是深、是淺。」「世尊！佛說法",
    "T16n0657_010:0203b25": "耶？」「堅意！不如凡夫所貪著說，隨智者所解，名",
    "T16n0657_010:0203b26": "為如來說法如。如來如實所知，無示無說。何",
    "T16n0657_010:0203b27": "以故？一切諸法不可說相，唯智者能知。凡",
    "T16n0657_010:0203b28": "夫若有所知，皆著文辭。是故佛說文字、語言，",
    "T16n0657_010:0203b29": "即非語言。」佛復告堅意：「一切諸法如日明淨，",
    "T16n0657_010:0203c01": "隨所正觀皆入無際。堅意！一切諸法皆能照",
    "T16n0657_010:0203c02": "明，能起一切智慧光故。堅意！一切諸法無所",
    "T16n0657_010:0203c03": "障礙，如虛空故。堅意！隨著二法，是中如來",
    "T16n0657_010:0203c04": "行無礙眼，堅意！是名法眼。佛以是眼見一切",
    "T16n0657_010:0203c05": "法無障礙相，堅意！是名諸法無障礙門。善男",
    "T16n0657_010:0203c06": "子、善女人若入是門，諸所言說皆有利益，皆",
    "T16n0657_010:0203c07": "無障礙，皆示義趣，皆說深義，無所貪著。「復次，",
    "T16n0657_010:0203c08": "堅意！諸法無垢，不染、不離。堅意！法無所屬，",
    "T16n0657_010:0203c09": "以不受故。堅意！一切法無邊，本末不可得故。",
    "T16n0657_010:0203c10": "堅意！諸有所說文字、語言，當知是中無有文",
    "T16n0657_010:0203c11": "字，亦無語言。堅意！是文字門云何有入？但說",
    "T16n0657_010:0203c12": "是法無有障礙，是名為入。堅意！如是入者，即",
    "T16n0657_010:0203c13": "名非入，入法性故。「堅意！如來所說諸三昧",
    "T16n0657_010:0203c14": "門，為何者是？堅意！有一相三昧，有眾相三昧。",
    "T16n0657_010:0203c15": "一相三昧者，有菩薩聞某世界有某如來，現",
    "T16n0657_010:0203c16": "在說法。菩薩取某佛相，以現在前，若坐道",
    "T16n0657_010:0203c17": "場，得無上菩提，若轉法輪，若與大眾圍遶說",
    "T16n0657_010:0203c18": "法；取如是相，以不亂念守攝諸根，心不馳散，",
    "T16n0657_010:0203c19": "專念一佛，不捨是緣，亦念是佛世界之相。而",
    "T16n0657_010:0203c20": "是菩薩於如來相及世界相，了達無相。常如",
    "T16n0657_010:0203c21": "是行，常如是觀，不離是緣，是時佛像即現在",
    "T16n0657_010:0203c22": "前而為說法。菩薩爾時深生恭敬，聽受是法，",
    "T16n0657_010:0203c23": "隨所信解，若深、若淺，轉加宗敬、尊重如來。菩",
    "T16n0657_010:0203c24": "薩住是三昧，聞說諸法皆壞敗相。聞已，受持，",
    "T16n0657_010:0203c25": "從三昧起，能為四眾演說是法。堅意！是名入",
    "T16n0657_010:0203c26": "一相三昧門。「復次，堅意！菩薩住是三昧，還",
    "T16n0657_010:0203c27": "能壞滅是佛相緣，亦壞自身；以是壞相壞一",
    "T16n0657_010:0203c28": "切法；壞一切法故，入一相三昧；從是三昧起，",
    "T16n0657_010:0203c29": "能為四眾解說是法。堅意！是名為入一相三",
    "T16n0657_010:0204a01": "昧門方便。「復次，堅意！菩薩緣是佛像，而作是",
    "T16n0657_010:0204a02": "念：『是像從何所來？我何所趣？』即知佛像無所",
    "T16n0657_010:0204a03": "從來，我無所至。菩薩爾時作是念言：『一切諸",
    "T16n0657_010:0204a04": "法亦復如是，無所從來、去無所至。』菩薩如是",
    "T16n0657_010:0204a05": "行、如是念，不久當得無礙法眼；得法眼已，便",
    "T16n0657_010:0204a06": "為諸佛之所知念，諸甚深法皆現在前；以是",
    "T16n0657_010:0204a07": "深法得無礙辯，雖講說法而不見法。堅意！如",
    "T16n0657_010:0204a08": "來於過去世無礙智慧，亦諸相中智無障礙，",
    "T16n0657_010:0204a09": "於過去世亦不作緣，亦非不知，不隨憶想。堅",
    "T16n0657_010:0204a10": "意！菩薩亦如是，住是三昧，雖演說法不見是",
    "T16n0657_010:0204a11": "法。菩薩住是三昧，深修習故，隨所聞因，緣第",
    "T16n0657_010:0204a12": "二佛，取相現前。若坐道場得無上菩提、若",
    "T16n0657_010:0204a13": "轉法輪、若於大眾圍遶說法，菩薩亦受持是",
    "T16n0657_010:0204a14": "第二佛法，亦不捨本佛相，亦見是佛，而是",
    "T16n0657_010:0204a15": "菩薩俱緣二佛，取相現前，聽受說法。堅意！是",
    "T16n0657_010:0204a16": "亦名為入一相三昧門。「復次，堅意！菩薩以善",
    "T16n0657_010:0204a17": "修習一佛相故，隨意自在，欲見諸佛皆能現",
    "T16n0657_010:0204a18": "前。堅意！譬如比丘心得自在，觀一切入取青",
    "T16n0657_010:0204a19": "色相，能得信解一切世界皆一青相。是人",
    "T16n0657_010:0204a20": "所緣唯一青色，觀內外法皆一青色，於是緣",
    "T16n0657_010:0204a21": "中得自在力故。堅意！菩薩亦復如是，隨其所",
    "T16n0657_010:0204a22": "聞諸佛名字、在何世界，即取是佛及世界",
    "T16n0657_010:0204a23": "相，皆緣現前。菩薩善修習此念佛緣故，觀諸",
    "T16n0657_010:0204a24": "世界盡皆作佛；常善修習是觀力故，便能",
    "T16n0657_010:0204a25": "了達一切諸緣皆為一緣，謂現在佛緣。是",
    "T16n0657_010:0204a26": "名得一相三昧門。」堅意白佛言：「世尊！以何方",
    "T16n0657_010:0204a27": "便得是三昧？」佛告堅意：「於是佛緣繫念，不散",
    "T16n0657_010:0204a28": "不離是緣，是名三昧門。堅意！以是一緣了",
    "T16n0657_010:0204a29": "達諸法，見一切法皆悉等相，是名一相三昧。",
    "T16n0657_010:0204b01": "菩薩住是三昧，又入法門，謂一切語皆如來",
    "T16n0657_010:0204b02": "語，一切有身皆如來身，不離如故。「復次，堅",
    "T16n0657_010:0204b03": "意！菩薩聞諸佛名，若二、若三、若四、若五、若十、",
    "T16n0657_010:0204b04": "二十、三十、四十、五十、若百、若千、若萬，若過是",
    "T16n0657_010:0204b05": "數，一時專念，盡現在前，及諸世界、弟子眾數，",
    "T16n0657_010:0204b06": "皆現在前，恭敬，尊重；亦念是佛具足妙身，形",
    "T16n0657_010:0204b07": "色相好，盡現在前，恭敬、尊重。亦復一一取三",
    "T16n0657_010:0204b08": "十二大人之相，及不虛行相、師子奮迅相、無",
    "T16n0657_010:0204b09": "見頂相、象王觀相、取大光相，以信解觀作",
    "T16n0657_010:0204b10": "無量相；亦取諸佛世界之相，以信解觀作無",
    "T16n0657_010:0204b11": "量淨相；亦取弟子眾，以信解觀作無量相。",
    "T16n0657_010:0204b12": "爾時，作是思惟：『如是諸佛從何所來？我何所",
    "T16n0657_010:0204b13": "至？』即知諸佛及以己身，無所從來亦無所至。",
    "T16n0657_010:0204b14": "如是觀知，如是信解，爾時菩薩作如是念：『如",
    "T16n0657_010:0204b15": "是事中，無有定法名為如來。』如是觀時，知一",
    "T16n0657_010:0204b16": "切法空、無所有，一相無相，用無相門入一切",
    "T16n0657_010:0204b17": "法，如是信解，達知一切諸法一相。堅意！菩",
    "T16n0657_010:0204b18": "薩能緣諸佛，繫念一處，是名眾相三昧門。「堅",
    "T16n0657_010:0204b19": "意！若是菩薩入是三昧，了達諸法一相無",
    "T16n0657_010:0204b20": "相，是名眾相三昧。菩薩住是三昧，所知、所見",
    "T16n0657_010:0204b21": "無非如來，又亦不見、不知如來；所知、所見無",
    "T16n0657_010:0204b22": "非是法，亦不見法；所有知、見皆佛弟子，亦",
    "T16n0657_010:0204b23": "不見、不知佛弟子眾；所知、所見無非說法，亦",
    "T16n0657_010:0204b24": "復不見、不知說法；所有見、知無非是緣，亦不",
    "T16n0657_010:0204b25": "見緣；所有見、知無非是辯，亦不見辯；諸有所",
    "T16n0657_010:0204b26": "見無非佛土，亦不見佛土；諸所有見無非世",
    "T16n0657_010:0204b27": "界，亦不見世界；諸所有見無非眾會，亦不",
    "T16n0657_010:0204b28": "見眾會。無法不說而無所說，無法不現亦無",
    "T16n0657_010:0204b29": "所現，無不信解亦無信解，無不分別亦無分",
    "T16n0657_010:0204c01": "別，無法不壞亦無所壞，無法不出亦無所出，",
    "T16n0657_010:0204c02": "無法不照亦無所照。堅意！是名諸菩薩三昧",
    "T16n0657_010:0204c03": "門。入是門者，當於諸法得無礙智。能如是觀，",
    "T16n0657_010:0204c04": "名無礙眼；於是事中亦不貪著，是名法眼。堅",
    "T16n0657_010:0204c05": "意！菩薩以是三昧能得無礙、無邊辯才。」爾",
    "T16n0657_010:0204c06": "時，堅意菩薩白佛言：「世尊！幾所菩薩於當來",
    "T16n0657_010:0204c07": "世成是三昧，能得無量、無邊辯才？何等菩薩",
    "T16n0657_010:0204c08": "於當來世成是三昧，能得無量、無邊辯才？」「堅",
    "T16n0657_010:0204c09": "意！菩薩若於後世，從比丘所聞是三昧，當知",
    "T16n0657_010:0204c10": "是比丘成是三昧，能得無邊無量辯才。堅",
    "T16n0657_010:0204c11": "意！如汝所問：幾所菩薩成是三昧，得無邊",
    "T16n0657_010:0204c12": "辯？若人常修是三昧者，此則能成。得是三",
    "T16n0657_010:0204c13": "昧，亦得無量無邊辯才。堅意！是門能開八百",
    "T16n0657_010:0204c14": "法藏，於今現在阿閦佛土諸菩薩者，常用是",
    "T16n0657_010:0204c15": "門。堅意！於是一門攝一切法門、諸三昧門，是",
    "T16n0657_010:0204c16": "名重句門。是故，堅意！若人如法欲入法門，是",
    "T16n0657_010:0204c17": "三昧門、重句門者，應當親近諸善知識，問：『云",
    "T16n0657_010:0204c18": "何行？云何觀察？云何修習？』當隨其教，如說修",
    "T16n0657_010:0204c19": "行。「堅意！若有四法，當知是為善知識也。何等",
    "T16n0657_010:0204c20": "為四？一、能令人入善法中；二、能障礙諸不善",
    "T16n0657_010:0204c21": "法；三、能令人住於正法；四、常能隨順教化。",
    "T16n0657_010:0204c22": "有是四法，當知即是善知識也。」爾時，世尊",
    "T16n0657_010:0204c23": "欲明此義而說偈言：",
    "T16n0657_010:0204c24": "「當近善知識，　　能障惡法者，",
    "T16n0657_010:0204c25": "能說佛所讚，　　是人應親近。",
    "T16n0657_010:0204c26": "隨佛道教化，　　能生人善法，",
    "T16n0657_010:0204c27": "如所聞安住，　　能增益智慧。",
    "T16n0657_010:0204c28": "可近法當近，　　應遠法當離，",
    "T16n0657_010:0204c29": "離於惡法已，　　當修佛所讚。",
    "T16n0657_010:0205a01": "若欲得辯才，　　亦欲演自智，",
    "T16n0657_010:0205a02": "當疾修是定，　　常隨善知識。",
    "T16n0657_010:0205a03": "隨所教修行，　　於法無祕悋，",
    "T16n0657_010:0205a04": "自所得善法，　　亦應為他說。",
    "T16n0657_010:0205a05": "深心行是法，　　捨離諸諂曲，",
    "T16n0657_010:0205a06": "常近善知識，　　修行如是法。",
    "T16n0657_010:0205a07": "故近善知識，　　應離惡知識，",
    "T16n0657_010:0205a08": "從是得多聞，　　疾得是三昧。",
    "T16n0657_010:0205a09": "「復次，堅意！若有四法，當知是為善知識相。何",
    "T16n0657_010:0205a10": "等為四？善知教化；善知修道；知教化過；知",
    "T16n0657_010:0205a11": "修道過。堅意！有是四法，當知是為善知識也。」",
    "T16n0657_010:0205a12": "爾時，世尊而說偈言：",
    "T16n0657_010:0205a13": "「知教化修道，　　亦知是過失，",
    "T16n0657_010:0205a14": "既知是法已，　　今住無礙法。",
    "T16n0657_010:0205a15": "「堅意！復有四法，當知是為善知識相。何謂",
    "T16n0657_010:0205a16": "為四？知地、知說、知人、知行。云何知地？隨人知",
    "T16n0657_010:0205a17": "地。云何知人？隨其所行能知，是人住多欲",
    "T16n0657_010:0205a18": "地，是人住多恚地，是人住多癡地，是人住",
    "T16n0657_010:0205a19": "定欲地，是人住定恚地，是人住定癡地，",
    "T16n0657_010:0205a20": "是人住定欲恚地，是人住定欲癡地，是人",
    "T16n0657_010:0205a21": "住定恚癡地，是人住定欲恚癡地。眾生若",
    "T16n0657_010:0205a22": "在三不善等諸地，皆悉能知，知已隨所住地",
    "T16n0657_010:0205a23": "如應教化。隨諸菩薩種種欲樂，皆悉能知。",
    "T16n0657_010:0205a24": "堅意！若人成是四法者，當知是為善知識",
    "T16n0657_010:0205a25": "也。「堅意！復有四法，當知是為善知識相。何",
    "T16n0657_010:0205a26": "謂為四？能調伏語；令人住甚深法中；能隨時",
    "T16n0657_010:0205a27": "教；隨時消息。」爾時，世尊即說偈言：",
    "T16n0657_010:0205a28": "「知隨人所行，　　諸地有差別，",
    "T16n0657_010:0205a29": "知隨地教化，　　故能速得成。",
    "T16n0657_010:0205b01": "能說法調伏，　　令住甚深法，",
    "T16n0657_010:0205b02": "隨時而呵責，　　亦隨時消息。",
    "T16n0657_010:0205b03": "雖有善好言，　　非時則不受，",
    "T16n0657_010:0205b04": "是故有智者，　　隨時而從捨。",
    "T16n0657_010:0205b05": "「堅意！復有四法，當知是為善知識相，則能",
    "T16n0657_010:0205b06": "令人修是三昧。何等為四？能令弟子出家行",
    "T16n0657_010:0205b07": "離；又能令人入深法觀；能令住定；於一切",
    "T16n0657_010:0205b08": "緣而無所礙，離於諸相。堅意！有是四法，當",
    "T16n0657_010:0205b09": "知是為善知識也。」佛說偈言：",
    "T16n0657_010:0205b10": "「若人讚出家，　　及行離住處，",
    "T16n0657_010:0205b11": "令弟子住中，　　是名善知識。",
    "T16n0657_010:0205b12": "令住第一義，　　甚深妙法中，",
    "T16n0657_010:0205b13": "令住無相定，　　是真善知識。",
    "T16n0657_010:0205b14": "「復次，堅意！菩薩若成四法，能修習是三昧。",
    "T16n0657_010:0205b15": "何謂為四？捨離自心，隨順師意；離於諸緣；為",
    "T16n0657_010:0205b16": "是三昧常勤精進，終不懈息；亦為欲得是三",
    "T16n0657_010:0205b17": "昧故，樂住閑處，離眾憒閙。菩薩若成是四",
    "T16n0657_010:0205b18": "法者，能得習是三昧。「堅意！菩薩復有四法，能",
    "T16n0657_010:0205b19": "疾得是三昧。何謂為四？善取佛相，乃至夢中",
    "T16n0657_010:0205b20": "亦見諸佛；善取說法相，乃至夢中亦得聞法；",
    "T16n0657_010:0205b21": "為眾生說而不疲惓；得深法忍壞諸法故，行",
    "T16n0657_010:0205b22": "無依定，隨離心故。堅意！菩薩有是四法，能疾",
    "T16n0657_010:0205b23": "得是三昧。」爾時，世尊說此偈言：",
    "T16n0657_010:0205b24": "「是人不捨，　　諸世尊相，　　常緣佛相，",
    "T16n0657_010:0205b25": "不離目前。　　具足見佛，　　相三十二，",
    "T16n0657_010:0205b26": "聽佛說法，　　諦取是相。　　於深必定，",
    "T16n0657_010:0205b27": "法中得忍，　　不依禪定，　　樂隨離心。",
    "T16n0657_010:0205b28": "非滅法故，　　壞裂諸法，　　諸法非法，",
    "T16n0657_010:0205b29": "是人所樂。　　觀諸相時，　　無所分別，",
    "T16n0657_010:0205c01": "信解諸法，　　皆是佛身。　　不著言辭，",
    "T16n0657_010:0205c02": "不隨他語，　　自知是相，　　亦為人說。",
    "T16n0657_010:0205c03": "菩薩若得，　　如是法忍，　　是名智者，",
    "T16n0657_010:0205c04": "逮是三昧。　　近善知識，　　修佛讚法，",
    "T16n0657_010:0205c05": "教化眾生，　　住深定法。　　堅意菩薩，",
    "T16n0657_010:0205c06": "若有四法，　　則能修習，　　逮是三昧。",
    "T16n0657_010:0205c07": "「何謂為四？善知緣相；善分別緣；善知轉緣；善",
    "T16n0657_010:0205c08": "知本行。有是四法，則能速成了達是定。」爾",
    "T16n0657_010:0205c09": "時，世尊而說偈言：",
    "T16n0657_010:0205c10": "「菩薩多聞有智者，　　應為他說是三昧，",
    "T16n0657_010:0205c11": "又從諸佛聞善法，　　亦應為人而演說。",
    "T16n0657_010:0205c12": "以緣佛身諦取相，　　修是寂滅妙三昧，",
    "T16n0657_010:0205c13": "又於諸世尊身相，　　深取種種差別相。",
    "T16n0657_010:0205c14": "三十二相及身相，　　形相色相光明相，",
    "T16n0657_010:0205c15": "面貌眉間白毫峙，　　當取如是人尊相。",
    "T16n0657_010:0205c16": "取是諸相在現前，　　常當觀察差別相，",
    "T16n0657_010:0205c17": "亦緣各各諸身分，　　不以一法為佛身。",
    "T16n0657_010:0205c18": "以心分析諸佛身，　　是心無形本性淨，",
    "T16n0657_010:0205c19": "雜雜隨緣念念滅，　　在緣會生各異相。",
    "T16n0657_010:0205c20": "既知心相不暫停，　　當知是緣亦生滅，",
    "T16n0657_010:0205c21": "是法皆從分別生，　　若無分別是最樂。",
    "T16n0657_010:0205c22": "善知心性是轉相，　　亦知諸緣是轉相，",
    "T16n0657_010:0205c23": "知世界空皆如炎，　　能知是已念不亂。",
    "T16n0657_010:0205c24": "能如是知諸法義，　　即能變化多佛相，",
    "T16n0657_010:0205c25": "而於佛相無所著，　　知諸世界皆空故。",
    "T16n0657_010:0205c26": "於諸緣中不取相，　　當知身心是轉相，",
    "T16n0657_010:0205c27": "如是法中能了達，　　故能疾得是三昧。",
    "T16n0657_010:0205c28": "於說法時現神力，　　亦於所說無錯謬，",
    "T16n0657_010:0205c29": "能令眾生起善福，　　亦能疾得如是法。",
    "T16n0657_010:0206a01": "「堅意！菩薩有四法能成是三昧，成已能為",
    "T16n0657_010:0206a02": "他說。何謂為四？為得是三昧故，勤行不息，晝",
    "T16n0657_010:0206a03": "夜經行；若欲坐時，先念諸佛坐於道場，今現",
    "T16n0657_010:0206a04": "在前；法施眾生，無所悋惜，於說法者現如世",
    "T16n0657_010:0206a05": "尊；分析自身，不依於法，以無依止為眾說",
    "T16n0657_010:0206a06": "法。菩薩能如是行、如是念、如是緣，安處法座，",
    "T16n0657_010:0206a07": "廣行法施，得是三昧，或有菩薩從法座起得",
    "T16n0657_010:0206a08": "是三昧。「復次，堅意！菩薩若成四法，得是三",
    "T16n0657_010:0206a09": "昧。何謂為四？菩薩為出家人，修遠離行，捨憒",
    "T16n0657_010:0206a10": "閙故；但畜三衣，離貪著故；於在家眾及出家",
    "T16n0657_010:0206a11": "眾不作諸緣，離非時過故；得深法忍，樂空寂",
    "T16n0657_010:0206a12": "故。堅意！菩薩成是四法，得是三昧。「堅意！",
    "T16n0657_010:0206a13": "在家菩薩若成四法，能得是三昧。何謂為四？",
    "T16n0657_010:0206a14": "菩薩若在居家，受持五戒；常日一食，依於塔",
    "T16n0657_010:0206a15": "廟；廣學多聞，達知諸論；亦應親近諸善知識，",
    "T16n0657_010:0206a16": "善能教化是三昧者。堅意！在家菩薩有是四",
    "T16n0657_010:0206a17": "法，能得是三昧。「復次，堅意！在家、出家菩薩",
    "T16n0657_010:0206a18": "若成四法，得是三昧。何謂為四？具足持戒，",
    "T16n0657_010:0206a19": "淨行活命，離諸疑悔；為是三昧不貪身命，不",
    "T16n0657_010:0206a20": "依於法；隨所從聞及能教化是三昧者，於是",
    "T16n0657_010:0206a21": "人中生世尊想；修習如是念佛三昧時，應",
    "T16n0657_010:0206a22": "離慳心。堅意！若有在家、出家菩薩有此四法，",
    "T16n0657_010:0206a23": "得是三昧。「堅意！若人發大乘心，欲得是三",
    "T16n0657_010:0206a24": "昧，當修四益法。何謂為四？應順觀身，不生身",
    "T16n0657_010:0206a25": "覺；應順觀受，不生受覺；應順觀心，不生心覺；",
    "T16n0657_010:0206a26": "應順觀法，不生法覺。堅意！菩薩成是四法者，",
    "T16n0657_010:0206a27": "助是三昧。」爾時，世尊欲明此義而說偈言：",
    "T16n0657_010:0206a28": "「菩薩應修習，　　佛所讚念處，",
    "T16n0657_010:0206a29": "比丘自行處，　　能得是三昧。",
    "T16n0657_010:0206b01": "常應分析身，　　亦不應依止，",
    "T16n0657_010:0206b02": "以無依止心，　　當得是三昧。",
    "T16n0657_010:0206b03": "於受心法中，　　亦無所依止，",
    "T16n0657_010:0206b04": "是法不思議，　　當得是三昧。",
    "T16n0657_010:0206b05": "應修習四禪，　　及修四正勤，",
    "T16n0657_010:0206b06": "不依止是法，　　當得是三昧。",
    "T16n0657_010:0206b07": "於四如意足，　　及四無礙智，",
    "T16n0657_010:0206b08": "當修習是法，　　莫生慳悋心。",
    "T16n0657_010:0206b09": "應安住戒中，　　親近善知識，",
    "T16n0657_010:0206b10": "說是三昧者，　　應生世尊想。",
    "T16n0657_010:0206b11": "以多聞為本，　　從是起三昧，",
    "T16n0657_010:0206b12": "隨諸佛所說，　　如教而修學。",
    "T16n0657_010:0206b13": "是名為上眼，　　法眼無有上，",
    "T16n0657_010:0206b14": "是中無障礙，　　以教化眾生。",
    "T16n0657_010:0206b15": "是眾經之本，　　能生多聞法，",
    "T16n0657_010:0206b16": "菩提從此成，　　是故常修學。",
    "T16n0657_010:0206b17": "佛所有十方，　　及四無礙智，",
    "T16n0657_010:0206b18": "皆從是中出，　　是故當修學。",
    "T16n0657_010:0206b19": "菩薩能得是，　　佛所說三昧，",
    "T16n0657_010:0206b20": "是人說法時，　　辯才不可盡。",
    "T16n0657_010:0206b21": "是人於諸法，　　能達知等相，",
    "T16n0657_010:0206b22": "如海無增減，　　無能窮竭者。",
    "T16n0657_010:0206b23": "若得是三昧，　　不隨他人教，",
    "T16n0657_010:0206b24": "若聽受法時，　　不觀他人說。",
    "T16n0657_010:0206b25": "諸天鬼龍王，　　夜叉緊陀羅，",
    "T16n0657_010:0206b26": "人非人眾等，　　觀菩薩所說。",
    "T16n0657_010:0206b27": "此下丹、鄉有　　皆言云何住？　　云何而修學？",
    "T16n0657_010:0206b28": "從何得此法？　　今為我等說。",
    "T16n0657_010:0206b29": "住是三昧故，　　知眾生深心，",
    "T16n0657_010:0206c01": "亦知心所樂，　　隨宜為說法。",
    "T16n0657_010:0206c02": "今我是經中，　　有所說諸佛，",
    "T16n0657_010:0206c03": "住是三昧故，　　悉知其名字。",
    "T16n0657_010:0206c04": "亦能知諸佛，　　所說種種法，",
    "T16n0657_010:0206c05": "隨心所緣念，　　即時皆能知。",
    "T16n0657_010:0206c06": "一切諸世尊，　　所有弟子眾，",
    "T16n0657_010:0206c07": "住是三昧故，　　皆悉能見知。",
    "T16n0657_010:0206c08": "知諸佛世界，　　種種莊嚴事，",
    "T16n0657_010:0206c09": "亦知彼受量，　　得是三昧故。",
    "T16n0657_010:0206c10": "知諸劫歲數，　　及日月時節，",
    "T16n0657_010:0206c11": "十方世界中，　　諸佛兩足尊。",
    "T16n0657_010:0206c12": "皆知是諸佛，　　亦知是佛土，",
    "T16n0657_010:0206c13": "亦知諸世尊，　　若干差別名。",
    "T16n0657_010:0206c14": "善修是三昧，　　故能悉知見，",
    "T16n0657_010:0206c15": "亦知諸世尊，　　所有弟子眾。",
    "T16n0657_010:0206c16": "為眾所說法，　　皆悉能知見，",
    "T16n0657_010:0206c17": "一切佛所行，　　及諸深妙法。",
    "T16n0657_010:0206c18": "善習三昧故，　　皆悉能知見，",
    "T16n0657_010:0206c19": "於未來世中，　　無量諸世尊。",
    "T16n0657_010:0206c20": "字名及種姓，　　一切悉見知，",
    "T16n0657_010:0206c21": "亦知其壽量，　　及諸弟子眾，",
    "T16n0657_010:0206c22": "所說諸經法，　　皆能悉了知，",
    "T16n0657_010:0206c23": "知諸佛世界，　　及種種莊嚴。",
    "T16n0657_010:0206c24": "諸佛滅度後，　　法住之久近，",
    "T16n0657_010:0206c25": "住是三昧中，　　皆悉知此事。",
    "T16n0657_010:0206c26": "故求多聞者，　　當修是三昧，",
    "T16n0657_010:0206c27": "常修是三昧，　　達知諸義趣。",
    "T16n0657_010:0206c28": "當知是三昧，　　入佛智初門，",
    "T16n0657_010:0206c29": "從是生眾生，　　亦生佛智慧，",
    "T16n0657_010:0207a01": "亦於中出生，　　無量諸福德。",
    "T16n0657_010:0207a02": "若有人發心，　　求無上菩提，",
    "T16n0657_010:0207a03": "盡供過去佛，　　及諸弟子眾，",
    "T16n0657_010:0207a04": "為供一一佛，　　及諸弟子眾，",
    "T16n0657_010:0207a05": "能捨滿三千，　　大千界珍寶，",
    "T16n0657_010:0207a06": "以爾所財寶，　　具滿一劫中，",
    "T16n0657_010:0207a07": "皆如是供給，　　諸佛及聖眾；",
    "T16n0657_010:0207a08": "於未來世中，　　所有諸世尊。",
    "T16n0657_010:0207a09": "亦皆盡供給，　　及諸弟子眾。",
    "T16n0657_010:0207a10": "堅意汝當知，　　是人所得福，",
    "T16n0657_010:0207a11": "求佛無上法，　　不可思議智。",
    "T16n0657_010:0207a12": "若人求佛道，　　修習是三昧，",
    "T16n0657_010:0207a13": "從是三昧故，　　多聞轉高勝。",
    "T16n0657_010:0207a14": "既得多聞已，　　廣為眾生說。",
    "T16n0657_010:0207a15": "是福過於彼，　　不可得思量，",
    "T16n0657_010:0207a16": "是福無有量，　　能增長智慧。",
    "T16n0657_010:0207a17": "若修是三昧，　　不須供諸佛，",
    "T16n0657_010:0207a18": "若以香塗香，　　衣食及湯藥，",
    "T16n0657_010:0207a19": "以此供諸佛，　　不名為真供。",
    "T16n0657_010:0207a20": "如來坐道場，　　所得微妙法，",
    "T16n0657_010:0207a21": "若人能修學，　　是真供諸佛。",
    "T16n0657_010:0207a22": "若求佛道者，　　欲得見諸佛，",
    "T16n0657_010:0207a23": "應勤修是法，　　疾得是三昧。",
    "T16n0657_010:0207a24": "若聞是三昧，　　能生歡喜心，",
    "T16n0657_010:0207a25": "當知是眾生，　　曾見數千佛。",
    "T16n0657_010:0207a26": "「復次，堅意！若善男子、善女人求佛道者，供給、",
    "T16n0657_010:0207a27": "嚴飾如來塔廟，則得具足四大淨願。何謂為",
    "T16n0657_010:0207a28": "四？能得第一淨妙色身；能得常生離諸難",
    "T16n0657_010:0207a29": "處，亦能堅心受持善法；能見諸佛，得不壞信；",
    "T16n0657_010:0207b01": "漸當逮得無上菩提，轉妙法輪；是名為四。」爾",
    "T16n0657_010:0207b02": "時，世尊欲明此義而說偈言：",
    "T16n0657_010:0207b03": "「智者能供給，　　諸佛尊塔廟，",
    "T16n0657_010:0207b04": "能具聖所讚，　　四種大淨法。",
    "T16n0657_010:0207b05": "常生離難處，　　能得正真見，",
    "T16n0657_010:0207b06": "常能見諸佛，　　見已心亦淨。",
    "T16n0657_010:0207b07": "得深信堅固，　　不動如須彌，",
    "T16n0657_010:0207b08": "畢定得佛智，　　速轉無上輪。",
    "T16n0657_010:0207b09": "35 囑累品(一〇)囑累品第三十五",
    "T16n0657_010:0207b10": "「復次，堅意！若善男子、善女人發大乘心，若佛",
    "T16n0657_010:0207b11": "現在、若滅度後，眾華瓔珞若上華香以為供",
    "T16n0657_010:0207b12": "養。以是緣故，得八具足：福身色具足、財",
    "T16n0657_010:0207b13": "物具足、眷屬具足、持戒具足、禪定具足、多",
    "T16n0657_010:0207b14": "聞具足、智慧具足、所願具足；是名八具足",
    "T16n0657_010:0207b15": "福。」爾時，世尊欲明此義即說偈言：",
    "T16n0657_010:0207b16": "「若求佛道者，　　供給佛塔廟，",
    "T16n0657_010:0207b17": "世世得福報，　　汝當一心聽。",
    "T16n0657_010:0207b18": "常具足身色，　　見者心得淨，",
    "T16n0657_010:0207b19": "福德大財富，　　及得善眷屬。",
    "T16n0657_010:0207b20": "安住於戒中，　　能深入禪定，",
    "T16n0657_010:0207b21": "得多聞智慧，　　無量如大海。",
    "T16n0657_010:0207b22": "諸有所願求，　　皆悉能具成，",
    "T16n0657_010:0207b23": "世間中尊上，　　第一良福田。",
    "T16n0657_010:0207b24": "以是善根故，　　得相三十二，",
    "T16n0657_010:0207b25": "相相各明顯，　　以是嚴其身。",
    "T16n0657_010:0207b26": "是一一諸相，　　以眾好嚴飾，",
    "T16n0657_010:0207b27": "一一諸相中，　　各有八十光；",
    "T16n0657_010:0207b28": "是一一光中，　　其明甚清徹，",
    "T16n0657_010:0207b29": "於八十種好，　　亦出諸光明。",
    "T16n0657_010:0207c01": "從諸善業緣，　　亦從願故生，",
    "T16n0657_010:0207c02": "隨諸願差別，　　故得如是相。",
    "T16n0657_010:0207c03": "足輪相一指，　　以眾好莊校，",
    "T16n0657_010:0207c04": "是福德神力，　　汝當一心聽。",
    "T16n0657_010:0207c05": "我是足指中，　　有好名照明，",
    "T16n0657_010:0207c06": "有光名極高，　　安住於此中，",
    "T16n0657_010:0207c07": "能演出光明，　　猶如過愛珠，",
    "T16n0657_010:0207c08": "是光如半月，　　在於須彌山。",
    "T16n0657_010:0207c09": "有相名堅集，　　有八十億光，",
    "T16n0657_010:0207c10": "諸光各有名，　　亦各有明色。",
    "T16n0657_010:0207c11": "我從一光邊，　　出千種色明，",
    "T16n0657_010:0207c12": "圍遶大千界，　　下方作佛事。",
    "T16n0657_010:0207c13": "我今若普放，　　善業所得光，",
    "T16n0657_010:0207c14": "世界若大小，　　一切皆迷悶。",
    "T16n0657_010:0207c15": "從是光現無量佛，　　遣到十方諸世界，",
    "T16n0657_010:0207c16": "廣化眾生作佛事，　　有如是等神通力。",
    "T16n0657_010:0207c17": "我有三昧能普照，　　用是三昧見世界，",
    "T16n0657_010:0207c18": "此三昧名須彌相，　　是中有光名善法。",
    "T16n0657_010:0207c19": "有三昧名首楞嚴，　　於一切中為最勝，",
    "T16n0657_010:0207c20": "因以淨心故能得，　　通達十方無罣礙。",
    "T16n0657_010:0207c21": "有人見佛現滅度，　　或有見佛初入胎，",
    "T16n0657_010:0207c22": "有人見生無所畏，　　其心安靜行七步，",
    "T16n0657_010:0207c23": "或有人見坐道場，　　謂我方今始成佛，",
    "T16n0657_010:0207c24": "又復見我轉法輪，　　又見修行菩薩道，",
    "T16n0657_010:0207c25": "汝等觀是三昧力，　　佛住是中得自在。",
    "T16n0657_010:0207c26": "有人知我壽劫數，　　或有知我壽半劫，",
    "T16n0657_010:0207c27": "有見我壽一小劫，　　若二三四若過是，",
    "T16n0657_010:0207c28": "有見我壽一億歲，　　又見過是若復少。",
    "T16n0657_010:0207c29": "此閻浮提世界人，　　知我壽命八十歲，",
    "T16n0657_010:0208a01": "又見我壽一日夜，　　又人知我壽長遠，",
    "T16n0657_010:0208a02": "或有三千大千界，　　謂我壽天一日夜。",
    "T16n0657_010:0208a03": "我知是人心喜樂，　　隨其所樂為說法，",
    "T16n0657_010:0208a04": "隨眾所應為示現，　　各各自謂為我說，",
    "T16n0657_010:0208a05": "見以歡喜生信解，　　是佛希有神通力。",
    "T16n0657_010:0208a06": "我若示汝所為事，　　一切凡夫皆狂惑，",
    "T16n0657_010:0208a07": "如來所行所為事，　　汝等設見亦不識，",
    "T16n0657_010:0208a08": "菩薩若知我深行，　　是人便能轉法輪。",
    "T16n0657_010:0208a09": "諸說法者各所樂，　　不能盡知我所行，",
    "T16n0657_010:0208a10": "若不能知普智行，　　是人所說甚微淺，",
    "T16n0657_010:0208a11": "若聞是法心退沒，　　我以是故無所說。",
    "T16n0657_010:0208a12": "若人能知普智行，　　是人心終不退沒，",
    "T16n0657_010:0208a13": "知一切法皆悉等，　　是人隨順我所行。",
    "T16n0657_010:0208a14": "堅意當知是諸經，　　於將來世無受者，",
    "T16n0657_010:0208a15": "唯除此會八菩薩，　　今於我前合掌立。",
    "T16n0657_010:0208a16": "堅意當知如是人，　　則能知我甚深行，",
    "T16n0657_010:0208a17": "亦為先會法之首，　　常能照然佛法炬，",
    "T16n0657_010:0208a18": "常教眾生菩提心，　　常為諸佛所稱歎。",
    "T16n0657_010:0208a19": "如今於我現前立，　　過去佛前亦如是，",
    "T16n0657_010:0208a20": "如恒沙數諸世尊，　　是人皆現於前立。",
    "T16n0657_010:0208a21": "時五百人從坐起，　　合掌白言當護法，",
    "T16n0657_010:0208a22": "皆是佛聽護法者，　　堅意汝亦在是數。",
    "T16n0657_010:0208a23": "復有八十菩薩起，　　皆為救護佛法故，",
    "T16n0657_010:0208a24": "世尊我於未來世，　　受持佛法如說行，",
    "T16n0657_010:0208a25": "當於濁亂惡世中，　　廣說流布是法種。",
    "T16n0657_010:0208a26": "世尊尋便為授記，　　即飛空中七多羅，",
    "T16n0657_010:0208a27": "八十億人得深喜，　　各各自聞得受記。」",
    "T16n0657_010:0208a28": "爾時佛告阿難曰：　　「汝能於後惡世中，",
    "T16n0657_010:0208a29": "受持如是諸經不？」　　答言：「世尊！我不堪。」",
    "T16n0657_010:0208b01": "佛知故問迦葉言：　　「汝能於我滅度後，",
    "T16n0657_010:0208b02": "受持如是諸經不？」　　答言：「世尊！我不堪。",
    "T16n0657_010:0208b03": "我能把持三千界，　　及大海水諸山林，",
    "T16n0657_010:0208b04": "諸餘麁重悉能持，　　不能惡世護持法。",
    "T16n0657_010:0208b05": "今世比丘多弊惡，　　不隨世尊所教法，",
    "T16n0657_010:0208b06": "何況世尊滅度後，　　誰能信受是深經？",
    "T16n0657_010:0208b07": "必當語我如是言，　　汝年老耄無智慧，",
    "T16n0657_010:0208b08": "云何反能教我等，　　利根聰辯解義者？",
    "T16n0657_010:0208b09": "世尊！如是弊惡人，　　樂世文頌外道論，",
    "T16n0657_010:0208b10": "捨離甚深禪定樂，　　皆悉樂著世俗事。",
    "T16n0657_010:0208b11": "多欲難滿無厭足，　　貪著美味求利養，",
    "T16n0657_010:0208b12": "我不能救是惡人，　　見已反增我憂惱。",
    "T16n0657_010:0208b13": "我在空閑獨處時，　　釋梵諸天來語我：",
    "T16n0657_010:0208b14": "『我世尊說如是法，　　令多眾生住聖道，",
    "T16n0657_010:0208b15": "有某比丘得無漏，　　某得神通到彼岸。』",
    "T16n0657_010:0208b16": "我聞是已心喜悅，　　而答釋言何足怪！",
    "T16n0657_010:0208b17": "於後惡世釋梵天，　　來至我所啼哭言：",
    "T16n0657_010:0208b18": "『大德當知佛法壞。』　　我聞是已懷憂惱，",
    "T16n0657_010:0208b19": "不能廣說是罪緣，　　亦復不能持此經，",
    "T16n0657_010:0208b20": "亦不能為作證明，　　惡世比丘難與言。」",
    "T16n0657_010:0208b21": "時諸天神皆啼哭，　　爾時佛告迦葉言：",
    "T16n0657_010:0208b22": "「我亦先知汝不能，　　受持擁護我法種，",
    "T16n0657_010:0208b23": "我諸聲聞弟子等，　　無能受持如是經。",
    "T16n0657_010:0208b24": "但諸菩薩承佛力，　　則能受持如是法，",
    "T16n0657_010:0208b25": "於後惡世或生疑，　　我今當斷此人惑。",
    "T16n0657_010:0208b26": "是經何故先來無，　　但是比丘自造作？",
    "T16n0657_010:0208b27": "或見是經多無量，　　為讀誦故心驚畏，",
    "T16n0657_010:0208b28": "是經廣博多散亂，　　誰能讀誦令究竟？",
    "T16n0657_010:0208b29": "若人今見汝問我，　　亦聞我今為汝說，",
    "T16n0657_010:0208c01": "是人於後甚惡世，　　能聞是經得歡喜。」",
    "T16n0657_010:0208c02": "佛說如是護法時，　　無量眾發菩提心，",
    "T16n0657_010:0208c03": "是諸眾生皆念言：　　「我於來世聽是法，",
    "T16n0657_010:0208c04": "後當供奉諸世尊，　　一心求覓佛大智，",
    "T16n0657_010:0208c05": "供給舍利及塔廟，　　種種嚴飾尊形像。」",
    "T16n0657_010:0208c06": "爾時，阿難從坐而起，偏袒右肩，右膝著地，合",
    "T16n0657_010:0208c07": "掌白佛言：「世尊！當何名為此經？云何受持？」",
    "T16n0657_010:0208c08": "佛告阿難：「此經名為『攝諸善根』，亦名『福德",
    "T16n0657_010:0208c09": "所依』，亦名『安慰諸菩薩心』，亦名『菩薩所問』，亦",
    "T16n0657_010:0208c10": "名『斷一切眾生疑』，當如是持。」佛說是經已，",
    "T16n0657_010:0208c11": "慧命阿難、堅意菩薩、諸天、龍、神、乾闥婆、阿修",
    "T16n0657_010:0208c12": "羅、人非人等一切大眾，皆大歡喜，信受佛語。",
    "T16n0657_010:0208c13": "佛說華手經卷第十"
}